joshlutils/Email.py
joshlutils/__init__.py
joshlutils/main.py
joshlutils-0.0.8.dist-info/METADATA
joshlutils-0.0.8.dist-info/WHEEL
joshlutils-0.0.8.dist-info/top_level.txt
joshlutils-0.0.8.dist-info/RECORD
