Metadata-Version: 2.1
Name: joshlutils
Version: 0.0.8
Summary: A simple utility package for various tasks I commonly perform
Home-page: https://github.com/JoshLoecker/utils
Author: Josh Loecker
Author-email: joshloecker@icloud.com
License: MIT
Download-URL: https://github.com/JoshLoecker/utils/archive/refs/tags/0.0.8.tar.gz
Keywords: Python,Python 3,Email
Platform: UNKNOWN
Requires-Python: >3.6
Requires-Dist: keyring
Requires-Dist: imap-tools
